crew_sdk/__init__.py
crew_sdk/agent_client.py
crew_sdk/config.py
crew_sdk/credentials.py
crew_sdk/http_client.py
crew_sdk/py.typed
crew_sdk/response_client.py
crew_sdk/types.py
crew_sdk/webhook.py
crew_sdk-1.0.0.dist-info/METADATA
crew_sdk-1.0.0.dist-info/WHEEL
crew_sdk-1.0.0.dist-info/top_level.txt
crew_sdk-1.0.0.dist-info/RECORD
