Metadata-Version: 2.4
Name: crew-sdk
Version: 1.0.0
Summary: Crewhive agent SDK for Python
Author: Crewhive
License: MIT
Project-URL: Homepage, https://github.com/crewhiveio/agent-sdk-python
Project-URL: Repository, https://github.com/crewhiveio/agent-sdk-python
Project-URL: Issues, https://github.com/crewhiveio/agent-sdk-python/issues
Requires-Python: >=3.9
Requires-Dist: requests>=2.31.0
